[
    {
        "SUB_DISTRICT_ID": 100502,
        "SUB_DISTRICT_NAME_THA": "อนุสาวรีย์",
        "SUB_DISTRICT_NAME_ENG": null,
        "PROVINCE_ID": 10,
        "DISTRICT_ID": 1005,
        "LAT": 13.868000030517578,
        "LONG": 100.60600280761719
    },
    {
        "SUB_DISTRICT_ID": 100508,
        "SUB_DISTRICT_NAME_THA": "ท่าแร้ง",
        "SUB_DISTRICT_NAME_ENG": null,
        "PROVINCE_ID": 10,
        "DISTRICT_ID": 1005,
        "LAT": 13.866000175476074,
        "LONG": 100.6500015258789
    }
]